pyudunits2/__init__.py
pyudunits2/__main__.py
pyudunits2/_datetime.py
pyudunits2/_exceptions.py
pyudunits2/_udunits2_xml_parser.py
pyudunits2/_unit.py
pyudunits2/_unit_reference.py
pyudunits2/_unit_system.py
pyudunits2/_version.py
pyudunits2/udunits2_combined.xml
pyudunits2/udunits2_combined.xml.README
pyudunits2/_expr/__init__.py
pyudunits2/_expr/atoms.py
pyudunits2/_expr/dimensionality.py
pyudunits2/_expr/expander.py
pyudunits2/_expr/graph.py
pyudunits2/_expr/normaliser.py
pyudunits2/_expr/split.py
pyudunits2/_expr/substitute.py
pyudunits2/_expr/sympy.py
pyudunits2/_grammar/.gitignore
pyudunits2/_grammar/README.md
pyudunits2/_grammar/__init__.py
pyudunits2/_grammar/compile.py
pyudunits2/_grammar/udunits2Lexer.g4.jinja
pyudunits2/_grammar/udunits2Parser.g4
pyudunits2/_grammar/_antlr4_runtime/BufferedTokenStream.py
pyudunits2/_grammar/_antlr4_runtime/CommonTokenFactory.py
pyudunits2/_grammar/_antlr4_runtime/CommonTokenStream.py
pyudunits2/_grammar/_antlr4_runtime/FileStream.py
pyudunits2/_grammar/_antlr4_runtime/InputStream.py
pyudunits2/_grammar/_antlr4_runtime/IntervalSet.py
pyudunits2/_grammar/_antlr4_runtime/LL1Analyzer.py
pyudunits2/_grammar/_antlr4_runtime/Lexer.py
pyudunits2/_grammar/_antlr4_runtime/ListTokenSource.py
pyudunits2/_grammar/_antlr4_runtime/Parser.py
pyudunits2/_grammar/_antlr4_runtime/ParserInterpreter.py
pyudunits2/_grammar/_antlr4_runtime/ParserRuleContext.py
pyudunits2/_grammar/_antlr4_runtime/PredictionContext.py
pyudunits2/_grammar/_antlr4_runtime/Recognizer.py
pyudunits2/_grammar/_antlr4_runtime/RuleContext.py
pyudunits2/_grammar/_antlr4_runtime/StdinStream.py
pyudunits2/_grammar/_antlr4_runtime/Token.py
pyudunits2/_grammar/_antlr4_runtime/TokenStreamRewriter.py
pyudunits2/_grammar/_antlr4_runtime/Utils.py
pyudunits2/_grammar/_antlr4_runtime/__init__.py
pyudunits2/_grammar/_antlr4_runtime/_antlr4_version.txt
pyudunits2/_grammar/_antlr4_runtime/atn/ATN.py
pyudunits2/_grammar/_antlr4_runtime/atn/ATNConfig.py
pyudunits2-0.1.dist-info/LICENSE
pyudunits2-0.1.dist-info/METADATA
pyudunits2-0.1.dist-info/WHEEL
pyudunits2-0.1.dist-info/top_level.txt
pyudunits2-0.1.dist-info/RECORD
