Metadata-Version: 2.2
Name: pyudunits2
Version: 0.1
Summary: A pure Python library designed for handling units of physical quantities, fully based on the UDUNITS2 grammar and XML database
Author-email: Phil Elson <pelson.pub@gmail.com>
Project-URL: Homepage, https://github.com/pelson/pyudunits2
Project-URL: Repository, https://github.com/pelson/pyudunits2
Classifier: Programming Language :: Python :: 3
Classifier: Operating System :: OS Independent
Requires-Python: >=3.10
License-File: LICENSE
Requires-Dist: sympy
Provides-Extra: xml
Requires-Dist: lxml; extra == "xml"
Provides-Extra: test
Requires-Dist: cf-units; extra == "test"
Requires-Dist: pytest; extra == "test"
Provides-Extra: doc
Provides-Extra: dev
Requires-Dist: jinja2; extra == "dev"
Requires-Dist: ruff; extra == "dev"
Requires-Dist: pyudunits2[doc,test]; extra == "dev"
